wordle/__init__.py
wordle/frequency.py
wordle/py.typed
wordle/utils.py
wordle-0.2.1.dist-info/LICENSE
wordle-0.2.1.dist-info/METADATA
wordle-0.2.1.dist-info/WHEEL
wordle-0.2.1.dist-info/top_level.txt
wordle-0.2.1.dist-info/RECORD
