Metadata-Version: 2.1
Name: wordle
Version: 0.2.1
Summary: Create a wordcloud for a Git repository.
Home-page: https://github.com/domdfcoding/wordle
Author: Dominic Davis-Foster
Author-email: dominic@davis-foster.co.uk
License: MIT License
Project-URL: Documentation, https://wordle.readthedocs.io/en/latest
Project-URL: Issue Tracker, https://github.com/domdfcoding/wordle/issues
Project-URL: Source Code, https://github.com/domdfcoding/wordle
Platform: Windows
Platform: macOS
Platform: Linux
Classifier: Development Status :: 3 - Alpha
Classifier: Intended Audience :: Developers
Classifier: License :: OSI Approved :: MIT License
Classifier: Operating System :: OS Independent
Classifier: Programming Language :: Python
Classifier: Programming Language :: Python :: 3 :: Only
Classifier: Programming Language :: Python :: 3.6
Classifier: Programming Language :: Python :: 3.7
Classifier: Programming Language :: Python :: 3.8
Classifier: Programming Language :: Python :: 3.9
Classifier: Programming Language :: Python :: Implementation :: CPython
Classifier: Topic :: Software Development :: Libraries :: Python Modules
Classifier: Topic :: Utilities
Classifier: Typing :: Typed
Requires-Python: >=3.6.1
Requires-Dist: domdf-python-tools (>=2.2.0)
Requires-Dist: dulwich (>=0.20.6)
Requires-Dist: pygments (>=2.7.4)
Requires-Dist: southwark (>=0.8.0)
Requires-Dist: wordcloud (>=1.8.0)
Requires-Dist: matplotlib (>=3.2.2) ; platform_machine != "aarch64" or python_version > "3.6"
Requires-Dist: matplotlib (==3.2.2) ; platform_machine == "aarch64" and python_version == "3.6"
Requires-Dist: numpy (>=1.19.2) ; platform_system != "Windows"
Requires-Dist: numpy (!=1.19.4,<1.20,>=1.19.3) ; platform_system == "Windows"
Provides-Extra: all
